test/__init__.py
test/test_account.py
test/test_account_response.py
test/test_account_response_data.py
test/test_accounts_api.py
test/test_accounts_response.py
test/test_accounts_response_data.py
test/test_budget_detail.py
test/test_budget_detail_response.py
test/test_budget_detail_response_data.py
test/test_budget_settings.py
test/test_budget_settings_response.py
test/test_budget_settings_response_data.py
test/test_budget_summary.py
test/test_budget_summary_response.py
test/test_budget_summary_response_data.py
test/test_budgets_api.py
test/test_bulk_response.py
test/test_bulk_response_data.py
test/test_bulk_response_data_bulk.py
test/test_bulk_transactions.py
test/test_categories_api.py
test/test_categories_response.py
test/test_categories_response_data.py
test/test_category.py
test/test_category_group.py
test/test_category_group_with_categories.py
test/test_category_response.py
test/test_category_response_data.py
test/test_currency_format.py
test/test_date_format.py
test/test_deprecated_api.py
test/test_error_detail.py
test/test_error_response.py
test/test_hybrid_transaction.py
test/test_hybrid_transactions_response.py
test/test_hybrid_transactions_response_data.py
test/test_month_detail.py
test/test_month_detail_response.py
test/test_month_detail_response_data.py
test/test_month_summaries_response.py
test/test_month_summaries_response_data.py
test/test_month_summary.py
test/test_months_api.py
test/test_payee.py
test/test_payee_location.py
test/test_payee_location_response.py
test/test_payee_location_response_data.py
test/test_payee_locations_api.py
test/test_payee_locations_response.py
test/test_payee_locations_response_data.py
test/test_payee_response.py
test/test_payee_response_data.py
test/test_payees_api.py
test/test_payees_response.py
test/test_payees_response_data.py
test/test_save_category_response.py
test/test_save_category_response_data.py
test/test_save_month_category.py
test/test_save_month_category_wrapper.py
test/test_save_sub_transaction.py
ynab_moka-1.0.1.dist-info/LICENSE
ynab_moka-1.0.1.dist-info/METADATA
ynab_moka-1.0.1.dist-info/WHEEL
ynab_moka-1.0.1.dist-info/top_level.txt
ynab_moka-1.0.1.dist-info/RECORD
