Metadata-Version: 2.1
Name: ynab-moka
Version: 1.0.1
Summary: YNAB API Endpoints
Home-page: https://github.com/dangior/ynab-moka
Author: UNKNOWN
Author-email: hello@garciadavid.net
License: UNKNOWN
Download-URL: https://github.com/dangior/ynab-moka/archive/1.0.1.tar.gz
Keywords: Swagger,YNAB API Endpoints
Platform: UNKNOWN
Requires-Dist: certifi (>=2017.4.17)
Requires-Dist: python-dateutil (>=2.1)
Requires-Dist: six (>=1.10)
Requires-Dist: urllib3 (>=1.23)
